mortise/__init__.py
mortise/mortise.py
mortise/testing.py
mortise-1.0.5.dist-info/LICENSE
mortise-1.0.5.dist-info/METADATA
mortise-1.0.5.dist-info/WHEEL
mortise-1.0.5.dist-info/top_level.txt
mortise-1.0.5.dist-info/RECORD
