Metadata-Version: 2.1
Name: mortise
Version: 1.0.5
Summary: Synchronous state machine framework for event driven systems
Home-page: https://github.com/keyme/mortise
Author: KeyMe Inc <opensource@key.me>
Author-email: UNKNOWN
License: MIT
Keywords: state fsm
Platform: UNKNOWN
Classifier: Development Status :: 5 - Production/Stable
Classifier: Intended Audience :: Developers
Classifier: Topic :: Software Development :: Libraries
Classifier: License :: OSI Approved :: MIT License
Classifier: Programming Language :: Python :: 3.4
Classifier: Programming Language :: Python :: 3.5
Classifier: Programming Language :: Python :: 3.6
